pypdx/__init__.py
pypdx/dbconn.py
pypdx/main.py
pypdx/parser.py
pypdx/data/approvedmfg.sql
pypdx/data/attachment.sql
pypdx/data/bom.sql
pypdx/data/init_pg_db.sql
pypdx/data/partsmaster.sql
pypdx/data/pdx-example.xml
pypdx-0.0.1b3.dist-info/DESCRIPTION.rst
pypdx-0.0.1b3.dist-info/METADATA
pypdx-0.0.1b3.dist-info/RECORD
pypdx-0.0.1b3.dist-info/WHEEL
pypdx-0.0.1b3.dist-info/entry_points.txt
pypdx-0.0.1b3.dist-info/metadata.json
pypdx-0.0.1b3.dist-info/top_level.txt
