Metadata-Version: 2.0
Name: pypdx
Version: 0.0.1b3
Summary: Extract information from a PDX XML file into a SQLite or PostgreSQL database
Home-page: https://github.com/sid5432/pypdx
Author: Sidney Li
Author-email: sidneyli5432@gmail.com
License: UNKNOWN
Keywords: PDX package data exchange IPC IPC-2571 IPC-2570
Platform: UNKNOWN
Classifier: Development Status :: 3 - Alpha
Classifier: Intended Audience :: Manufacturing
Classifier: Topic :: Utilities
Classifier: License :: OSI Approved :: Apache Software License
Classifier: Programming Language :: Python :: 2
Classifier: Programming Language :: Python :: 2.7
Classifier: Programming Language :: Python :: 3
Classifier: Programming Language :: Python :: 3.4
Classifier: Programming Language :: Python :: 3.5
Classifier: Programming Language :: Python :: 3.6
Requires-Dist: psycopg2
Requires-Dist: xmltodict
Provides-Extra: test
Requires-Dist: pytest; extra == 'test'
